gather_urls/__init__.py
gather_urls/gather_urls.py
link_finder-0.1.2.dist-info/LICENSE
link_finder-0.1.2.dist-info/METADATA
link_finder-0.1.2.dist-info/WHEEL
link_finder-0.1.2.dist-info/entry_points.txt
link_finder-0.1.2.dist-info/top_level.txt
link_finder-0.1.2.dist-info/RECORD
